{
    "Name": "Nakama 1a Chapter 2 Vocabulary",
    "ObjectName": "word",
    "AnswerName": "translation",
    "Author": "976",
    "Visibility": "public",
    "Set": [
        {"アジアけんきゅう": "Asian Studies"},
        {"アメリカ": "America/the United States"},
        {"イギリス": "England"},
        {"いちねんせ": "freshman/first-year student"},
        {"いま": "now"},
        {"えいご": "English"},
        {"オーストラリア": "Australia"},
        {"がくせい": "student"},
        {"カナダ": "Canada"},
        {"かんこく": "South Korea"},
        {"けえいえがく": "management/business administration"},
        {"こうがく": "engineering"},
        {"こうこう": "high school"},
        {"ごご": "p.m./pm/afternoon"},
        {"ごぜん": "a.m./am/morning"},
        {"こちら": "this person/this way"},
        {"さんねんせい": "junior/third-year student"},
        {"しゅっしん": "one's native country/hometown/birthplace/alma mater"},
        {"スペイン": "Spain"},
        {"せんこう": "major"},
        {"だいがく": "college/university"},
        {"だいがくいんせい": "graduate student"},
        {"だいがくせい": "college student"},
        {"たいわん": "Taiwan"},
        {"ちゅうごく": "China"},
        {"なまえ": "name"},
        {"にねんせい": "sophomore/second-year student"},
        {"にほん": "Japan"},
        {"ビジネス": "business"},
        {"フランス": "France"},
        {"ぶんがく": "literature"},
        {"メキシコ": "Mexico"},
        {"よねんせい": "senior/fourth-year student"},
        {"らいねん": "next year"},
        {"りゅうがくせい": "foreign student"},
        {"れきし": "history"},
        {"ぼく": "I/Male"},
        {"わたし": "I/Male and Female"}
    ]
}