{"Name":"Chapter 10 vocabulary","ObjectName":"word","AnswerName":"definition","Set":[{"あし・足":"leg/foot"},{"あたま・頭":"head"},{"あに・兄":"the speaker's older brother/older brother"},{"あね・姉":"the speaker's older sister/older sister"},{"いもうと・妹":"the speaker's younger sister/younger sister"},{"いもうとさん・妹さん":"someone else's younger sister/younger sister"},{"おかあさん・お母さん":"someone else's mother/mother"},{"おくさん・奥さん":"someone else's wife/wife"},{"おこさん・お子さん":"someone else's child/child"},{"おじいさん・お祖父さん":"someone else's grandfather/grandfather"},{"おとうさん・お父さん":"someone else's father/father"},{"おとうと・弟":"the speaker's younger brother/younger brother"},{"おとうとさん・弟さん":"someone else's younger brother/younger brother"},{"おとこ・男":"male"},{"おにいさん・お兄さん":"someone else's older brother"},{"おねえさん・お姉さん":"someone else's older sister"},{"おばあさん・お祖母さん":"someone else's grandmother"},{"おんな・女":"female"},{"かいしゃいん・会社員":"businessperson"},{"かお・顔":"face"},{"かぞく・家族":"the speaker's family/family"},{"かみ・神様":"hair"},{"きょうだい・兄弟":"siblings"},{"くち・口":"mouth"},{"けっこん・結婚":"marriage/to marry/to marry (suru verb) "},{"こ・子":"child"},{"ごかぞく・ご家族":"someone else's family/family"},{"ごしゅじん・ご主人":"someone else's siblings/siblings"},{"こども・子供":"child"},{"しゅじん・主人":"the speaker's husband/husband"},{"せ・背":"back (part of the body)/back/height (of a person)/height"},{"そふ・祖父":"the speaker's grandfather/grandfather"},{"そぼ・祖母":"the speaker's grandmother/grandmother"},{"ちち・父":"the speaker's father/father"},{"つま・妻":"the speaker's wife/wife"},{"て・手":"hand"},{"とし・年":"age"},{"はな・鼻":"nose"},{"はは・母":"the speaker's mother/mother"},{"ひとりっこ・一人っ子":"only child"},{"まんなか・真ん中":"center/middle/middle child"},{"みみ・耳":"ear"},{"目":"eye"},{"めがね・眼鏡":"glasses"},{"かぶる":"to put on (a hat or cap)/to put on"},{"すむ・住む":"to reside"},{"はく":"to put on (skirt, pants, socks, shoes)/to put on"},{"ふとる":"to gain weight"},{"わかる・分かる":"to understand"},{"かける":"to put on (glasses)/to put on"},{"きる・着る":"to put on (sweater, shirt, jacket)/to put on"},{"つとめる・勤める":"to become employed"},{"やせる":"to lose weight"},{"する":"to put on (accessories)"},{"～ている":"resultant state"},{"あかるい・明るい":"bright/cheerful"},{"かっこい":"good-looking/cool/neat"},{"かわいい・可愛い":"cute/adorable"},{"しかくい・四角い":"square"},{"ながい・長い":"long"},{"ほぞながい・細長い":"long/elongated"},{"みるい・丸い":"round"},{"みじかい・短い":"short (length)/short"},{"じょうず（な）・上手（な）":"good at/skillful"},{"じんせつ（な）・親切（な）":"kind"},{"いくつ":"how old"},{"しょう～・小～":"elementary (school)/elementary"},{"ちゅう～・中～":"middle (school)/middle"},{"～さい・～歳・～才":"years old"},{"～にん・～人":"people"},{"～ばん（め）・～番（目）":"th (ordinal suffix)/th"},{"～かた・～方":"person"},{"いいえ、そんなことは　ありません。":"No, that's not the case."},{"いいえ、まだまだです。":"No, I still have a long way to go."},{"あたまがいい・頭がいい":"smart/intelligent"},{"としうえ・年上":"elder"},{"としした・年下":"younger"},{"ブロンド":"blonde/blond"}],"Visibility":"public","Notes":"Chapter 10 vocabulary from Nakama 1/Nakama 1b.\n\nAlso, if you couldn't tell, chapters 8~12 lose the structure of learning progressively that was happening through 1~7 and start checking off boxes so you can pass for JLPTN5 fluency. (Or was JLPT made from the same standards? We'll never know...)","Author":"976","examples":{"かいしゃいん・会社員":"かいしゃいんですか？\nAre you an employee?\n\nEnglish translation: Are you an employee?","あし・足":"あしが痛いです。\nMy foot hurts.","あに・兄":"あには大学生です。\nMy older brother is a college student.","あたま・頭":"あたまが痛いです。\nMy head hurts.","おくさん・奥さん":"彼は幸せな人生を奥さんと過ごしています。\nTranslation: He is living a happy life with his wife.","おじいさん・お祖父さん":"おじいさんは毎日公園で散歩します。\nTranslation: The grandfather walks in the park every day.","おとうさん・お父さん":"おとうさんは仕事に行きます。\nOtousan wa shigoto ni ikimasu.\nMy father goes to work.","おとうと・弟":"おとうとはまだ中学生です。\n(My) younger brother is still a middle school student.","おにいさん・お兄さん":"おにいさん、お兄さん、ありがとう！\nOniisan, oniisan, arigatou!\nThank you, big brother!","おねえさん・お姉さん":"おねえさん、今日はどこに行くの？\nOneesan, where are you going today?","おんな・女":"おんなですか。\nAre you a woman?","おとこ・男":"おとこがパンを食べています。\nTranslation: The man is eating bread.","かぞく・家族":"かぞくが大切です。\nKazoku ga taisetsu desu.\nFamily is important.","かみ・神様":"彼女のかみはとてもきれいです。\nHer hair is very beautiful.","かお・顔":"私のかおを見てください。\nPlease look at my face.","きょうだい・兄弟":"私は3人きょうだいです。\n(I have three siblings.)\n\nEnglish translation: I have three siblings."}}