{"Name":"Nakama Chapter 8 Counters Flipped","ObjectName":"count","AnswerName":"phrase","Set":[{"1 general counter":"ひとつ/一つ/hitotsu"},{"2 general counter":"ふたつ/二つ/futatsu"},{"3 general counter":"みっつ/三つ/mittsu"},{"4 general counter":"よっつ/四つ/yottsu"},{"5 general counter":"いつつ/五つ/itsutsu"},{"6 general counter":"むっつ/六つ/muttsu"},{"7 general counter":"ななつ/七つ/nanatsu"},{"8 general counter":"やっつ/八つ/yattsu"},{"9 general counter":"ここのつ/九つ/kokonotsu"},{"10 general counter":"とお/too"},{"1 person":"一人/ひとり/hitori"},{"2 people":"二人/ふたり/futari"},{"3 people":"三人/さんにん/sannin"},{"4 people":"四人/よにん/yonin"},{"5 people":"五人/ごにん/gonin"},{"6 people":"六人/ろくにん/rokunin"},{"7 people":"七人/しちにん/shichinin"},{"8 people":"八人/はちにん/hachinin"},{"9 people":"九人/くにん/kunin"},{"10 people":"十人/じゅうにん/juunin"},{"1 thin, flat object":"一枚/いちまい/ichimai"},{"2 thin, flat objects":"二枚/にまい/nimai"},{"3 thin, flat objects":"三枚/さんまい/sanmai"},{"4 thin, flat objects":"四枚/よんまい/yonmai"},{"5 thin, flat objects":"五枚/ごまい/gomai"},{"6 thin, flat objects":"六枚/ろくまい/rokumai"},{"7 thin, flat objects":"七枚/ななまい/nanamai"},{"8 thin, flat objects":"八枚/はちまい/hachimai"},{"9 thin, flat objects":"九枚/きゅうまい/kyuumai"},{"10 thin, flat objects":"十枚/じゅうまい/juumai"},{"1 cylindrical object":"一本/いっぽん/ippon"},{"2 cylindrical objects":"二本/にほん/nihon"},{"3 cylindrical objects":"三本/さんぼん/sanbon"},{"4 cylindrical objects":"四本/よんほん/yonhon"},{"5 cylindrical objects":"五本/ごほん/gohon"},{"6 cylindrical objects":"六本/ろっぽん/roppon"},{"7 cylindrical objects":"七本/ななほん/nanahon"},{"8 cylindrical objects":"八本/はっぽん/happon"},{"9 cylindrical objects":"九本/きゅうほん/kyuuhon"},{"10 cylindrical objects":"十本/じゅっぽん/juppon"},{"1 fish, animal":"一匹/いっぴき/ippiki"},{"2 fish, animals":"二匹/にひき/nihiki"},{"3 fish, animals":"三匹/さんびき/sanbiki"},{"4 fish, animals":"四匹/よんひき/yonnhiki"},{"5 fish, animals":"五匹/ごひき/gohiki"},{"6 fish, animals":"六匹/ろっぴき/roppiki"},{"7 fish, animals":"七匹/ななひき/nanahiki"},{"8 fish, animals":"八匹/はっぴき/happiki"},{"9 fish, animals":"九匹/きゅうひき/kyuuhiki"},{"10 fish, animals":"十匹/じゅっぴき/juppiki"},{"1 bound objects":"一冊/いっさつ/issatsu"},{"2 bound objects":"二冊/にさつ/nisatsu"},{"3 bound objects":"三冊/さんさつ/sansatsu"},{"4 bound objects":"四冊/よんさつ/yonsatsu"},{"5 bound objects":"五冊/ごさつ/gosatsu"},{"6 bound objects":"六冊/ろくさつ/rokusatsu"},{"7 bound objects":"七冊/ななさつ/nanasatsu"},{"8 bound objects":"八冊/はっさつ/hassatsu"},{"9 bound objects":"九冊/きゅうさつ/kyuusatsu"},{"10 bound objects":"十冊/じゅっさつ/jussatsu"},{"how many thin, flat objects":"何枚/なんまい/nanmai"},{"how many cylindrical objects":"何本/なんぼん/nanbon"},{"how many fish, animals":"何匹/なんびき/nanbiki"},{"how many bound objects":"何冊/なんさつ/nansatsu"}],"Visibility":"public","Notes":"Nakama 1 Ch.8's counters + 円 & 階 + Japanese Origin Numbers/General Counters + People\n<br>You can find all of this in Appendix D in the Nakama 1 Combined Second Student Edition. (I don't know what it is in the Nakama 1B one.)","Author":"976","examples":{"9 fish, animals":"九匹の猫が庭で遊んでいます。\nTranslation: Nine cats are playing in the garden.","4 bound objects":"図書館で四冊の本を借りました。\nI borrowed four books from the library.","7 bound objects":"図書館で七冊の本を借りました。\nI borrowed seven books from the library.","5 bound objects":"図書館で本を五冊借りました。\nI borrowed five books from the library.","2 fish, animals":"その池には魚が二匹います。\nThere are two fish in the pond.","9 bound objects":"九冊の本を買いました。\nI bought nine bound books.","1 fish, animal":"魚が一匹います。\nTranslation: There is one fish.","1 bound objects":"その本は一冊だけあります。\nThere is only one bound object.","8 people":"今日のパーティーには八人の友達が来ます。\nEnglish: Eight people will come to today's party.","5 cylindrical objects":"その部屋には、五本の円柱形の物体があります。\n\nThere are 5 cylindrical objects in the room.","2 thin, flat objects":"机の上に二枚の紙が置いてあります。\n\nThere are two thin, flat objects (pieces of paper) placed on the desk.","5 thin, flat objects":"五枚の葉書を送ります。\nI will send five postcards.","8 fish, animals":"八匹の猫が庭で遊んでいます。\nEight cats are playing in the garden.\n\n(Note: The counter 匹/hiki is used for small animals like cats, dogs, and fish in Japanese.)","2 general counter":"その本屋で本を二つ買いました。\nI bought two books at the bookstore.","9 thin, flat objects":"九枚のカードを持っています。\nI have nine thin, flat objects.","3 general counter":"その本棚にはみっつの本があります。\nThere are three books on that bookshelf.\n\n三つ/みっつ/mittsu","6 thin, flat objects":"六枚の紙を持っています。\nI have six thin, flat objects.","7 general counter":"お箸を七つください。\nEnglish Translation: Can I have seven pairs of chopsticks, please?","5 people":"今日のパーティーには、５人しか来ませんでした。\n\nEnglish translation: Only five people came to today's party.","3 cylindrical objects":"その机の上には三本のペンがあります。\n\nEnglish: There are three cylindrical objects on the desk.","6 cylindrical objects":"六本の円柱形の物体が机の上に並んでいます。\n\nSix cylindrical objects are lined up on the desk.","8 cylindrical objects":"八本の円柱形の物体\n\nEight cylindrical objects","1 thin, flat object":"そのテーブルに一枚の紙が置いてあります。\nOn the table, there is a thin, flat object.","10 bound objects":"図書館で十冊の本を借りました。\nI borrowed 10 bound objects from the library.","6 fish, animals":"魚と動物を合わせると、合計で六匹です。\nWhen you combine fish and animals, the total is six.","how many cylindrical objects":"何本の円筒形の物体がありますか？\n\nHow many cylindrical objects are there?","how many thin, flat objects":"何枚ありますか。\n\nHow many thin, flat objects are there?","how many bound objects":"何冊の本を買いましたか？\nEnglish: How many bound objects did you buy?","how many fish, animals":"何匹の魚や動物がいますか？\n\nEnglish translation: How many fish, animals are there?","10 fish, animals":"１０匹の魚や動物がいる。\nThere are 10 fish and animals.\n\n十匹/じゅっぴき/juppiki.","5 general counter":"カレンダーには五つの星印があります。\nOn the calendar, there are five star marks.","10 people":"パーティーに十人の友達が来ました。\nTen friends came to the party.\n\n十人: 10 people","4 general counter":"その本を四つ買いました。\nI bought four books.","7 people":"七人の友達とパーティーに行きます。\n\nEnglish: I will go to the party with 7 friends.","9 people":"今日の食事会には九人の友達が来ます。\nEnglish: Nine people will come to today's dinner party.","3 people":"三人で映画を見に行きます。\nSan-nin de eiga o mi ni ikimasu.\nThree people are going to see a movie together.","6 general counter":"その店でリンゴを六つ買いました。\nI bought six apples at that store.","10 cylindrical objects":"その箱には十本の円柱形の物が入っています。\n\nEnglish: There are 10 cylindrical objects in that box.","1 general counter":"その本を一つください。\nPlease give me one of those books.","7 cylindrical objects":"七本の円柱形の物体\n\nSeven cylindrical objects","10 thin, flat objects":"10枚の薄い平らな物\n10 thin, flat objects","9 cylindrical objects":"九本の円柱形の物体\nNine cylindrical objects.","1 cylindrical object":"その机の上には一本のペンがあります。\n\nEnglish: There is a cylindrical pen on the desk.","7 thin, flat objects":"七枚の葉書を送ります。\nI will send seven thin, flat postcards.","6 bound objects":"私は本棚に六冊の漫画を置いた。\n\nI put six bound manga books on the bookshelf.","8 bound objects":"八冊の本を図書館から借りました。\nI borrowed 8 bound books from the library."}}